setup.py
sucrose/__init__.py
sucrose.egg-info/PKG-INFO
sucrose.egg-info/SOURCES.txt
sucrose.egg-info/dependency_links.txt
sucrose.egg-info/not-zip-safe
sucrose.egg-info/requires.txt
sucrose.egg-info/top_level.txt
sucrose/app/__init__.py
sucrose/app/runserver.py