Metadata-Version: 1.0
Name: sucrose
Version: 0.1
Summary: mircroservice library using flask and rabbitmq
Home-page: http://github.com/diaphel/sucrose
Author: Diaphel Thompson
Author-email: diaphel@icloud.com
License: Diaphel
Platform: UNKNOWN
